cei_crawler/__init__.py
cei_crawler/crawler.py
cei_crawler/pages.py
cei_crawler-1.0.3.dist-info/LICENSE.txt
cei_crawler-1.0.3.dist-info/METADATA
cei_crawler-1.0.3.dist-info/WHEEL
cei_crawler-1.0.3.dist-info/top_level.txt
cei_crawler-1.0.3.dist-info/RECORD
