Metadata-Version: 2.1
Name: cei-crawler
Version: 1.0.3
Summary: cei.com.br crawler
Home-page: https://github.com/victorclc/cei-crawler
Author: Victor Corte
Author-email: victorcortelc@gmail.com
License: MIT
Platform: UNKNOWN
